devopsforge/__init__.py
devopsforge/__main__.py
devopsforge/cli/__init__.py
devopsforge/cli/main.py
devopsforge/core/__init__.py
devopsforge/core/analyzer.py
devopsforge/templates/__init__.py
devopsforge/templates/cicd_generator.py
devopsforge/templates/dockerfile_generator.py
devopsforge-0.1.0.dist-info/licenses/LICENSE
tests/__init__.py
tests/conftest.py
tests/test_analyzer.py
tests/test_cli.py
tests/test_templates.py
devopsforge-0.1.0.dist-info/METADATA
devopsforge-0.1.0.dist-info/WHEEL
devopsforge-0.1.0.dist-info/entry_points.txt
devopsforge-0.1.0.dist-info/top_level.txt
devopsforge-0.1.0.dist-info/RECORD
